LICENSE
MANIFEST.in
README.rst
requirements.txt
setup.py
pyvcloud/__init__.py
pyvcloud/gateway.py
pyvcloud/score.py
pyvcloud/vapp.py
pyvcloud/vcloudair.py
pyvcloud/vcloudsession.py
pyvcloud.mishkin.egg-info/PKG-INFO
pyvcloud.mishkin.egg-info/SOURCES.txt
pyvcloud.mishkin.egg-info/dependency_links.txt
pyvcloud.mishkin.egg-info/requires.txt
pyvcloud.mishkin.egg-info/top_level.txt
pyvcloud.mishkin.egg-info/zip-safe
pyvcloud/helper/CommonUtils.py
pyvcloud/helper/__init__.py
pyvcloud/schema/__init__.py
pyvcloud/schema/vcd/__init__.py
pyvcloud/schema/vcd/schemas/versioning/versionsType.py
pyvcloud/schema/vcd/v1_5/__init__.py
pyvcloud/schema/vcd/v1_5/schemas/__init__.py
pyvcloud/schema/vcd/v1_5/schemas/admin/__init__.py
pyvcloud/schema/vcd/v1_5/schemas/admin/vCloudEntities.py
pyvcloud/schema/vcd/v1_5/schemas/vcloud/__init__.py
pyvcloud/schema/vcd/v1_5/schemas/vcloud/catalogItemType.py
pyvcloud/schema/vcd/v1_5/schemas/vcloud/catalogType.py
pyvcloud/schema/vcd/v1_5/schemas/vcloud/commonType.py
pyvcloud/schema/vcd/v1_5/schemas/vcloud/diskType.py
pyvcloud/schema/vcd/v1_5/schemas/vcloud/entityType.py
pyvcloud/schema/vcd/v1_5/schemas/vcloud/mediaType.py
pyvcloud/schema/vcd/v1_5/schemas/vcloud/networkType.py
pyvcloud/schema/vcd/v1_5/schemas/vcloud/organizationListType.py
pyvcloud/schema/vcd/v1_5/schemas/vcloud/organizationType.py
pyvcloud/schema/vcd/v1_5/schemas/vcloud/queryRecordViewType.py
pyvcloud/schema/vcd/v1_5/schemas/vcloud/sessionType.py
pyvcloud/schema/vcd/v1_5/schemas/vcloud/taskType.py
pyvcloud/schema/vcd/v1_5/schemas/vcloud/tasksListType.py
pyvcloud/schema/vcd/v1_5/schemas/vcloud/vAppTemplateType.py
pyvcloud/schema/vcd/v1_5/schemas/vcloud/vAppType.py
pyvcloud/schema/vcd/v1_5/schemas/vcloud/vcloudType.py
pyvcloud/schema/vcd/v1_5/schemas/vcloud/vdcType.py
pyvcloud/schema/vcd/v1_5/schemas/vcloud/vmsType.py
pyvcloud/schema/vchs/__init__.py
pyvcloud/schema/vchs/ondemand/__init__.py
pyvcloud/schema/vchs/ondemand/sc/__init__.py
pyvcloud/schema/vchs/ondemand/sc/sc/__init__.py
pyvcloud/schema/vchs/ondemand/sc/sc/bindingType.py
pyvcloud/schema/vchs/ondemand/sc/sc/instanceType.py
pyvcloud/schema/vchs/ondemand/sc/sc/serviceplanType.py
pyvcloud/schema/vcim/__init__.py
pyvcloud/schema/vcim/baseType.py
