Metadata-Version: 1.1
Name: pyvcloud.mishkin
Version: 12.3
Summary: VMware vCloud Python SDK
Home-page: https://github.com/vmware/pyvcloud
Author: VMware, Inc.
Author-email: pgomez@vmware.com
License: License :: OSI Approved :: Apache Software License
Keywords: pyvcloud vcloud vcloudair vmware
Platform: Windows
Platform: Linux
Platform: Solaris
Platform: Mac OS-X
Platform: Unix
Classifier: Development Status :: 1 - Planning
Classifier: License :: OSI Approved :: Apache Software License
Classifier: Intended Audience :: Information Technology
Classifier: Intended Audience :: System Administrators
Classifier: Intended Audience :: Developers
Classifier: Environment :: No Input/Output (Daemon)
Classifier: Programming Language :: Python :: 2
Classifier: Programming Language :: Python :: 2.6
Classifier: Programming Language :: Python :: 2.7
Classifier: Programming Language :: Python :: 3
Classifier: Programming Language :: Python :: 3.2
Classifier: Programming Language :: Python :: 3.3
Classifier: Programming Language :: Python :: 3.4
Classifier: Topic :: Software Development :: Libraries :: Python Modules
Classifier: Topic :: System :: Distributed Computing
Classifier: Operating System :: Microsoft :: Windows
Classifier: Operating System :: POSIX
Classifier: Operating System :: Unix
Classifier: Operating System :: MacOS
